rayoptics/__init__.py
rayoptics/coord_geometry_types.py
rayoptics/environment.py
rayoptics/typing.py
rayoptics/codev/__init__.py
rayoptics/codev/cmdproc.py
rayoptics/codev/reader.py
rayoptics/codev/tla.py
rayoptics/codev/tla_mapping.csv
rayoptics/codev/tests/CODV_32327.seq
rayoptics/codev/tests/CODV_49664.seq
rayoptics/codev/tests/CODV_65564.seq
rayoptics/codev/tests/CODV_65988.seq
rayoptics/codev/tests/CODV_65988_noDOE.seq
rayoptics/codev/tests/achroMangin.seq
rayoptics/codev/tests/achroMangin_ok.seq
rayoptics/codev/tests/ag_dblgauss.csv
rayoptics/codev/tests/ag_dblgauss.lis
rayoptics/codev/tests/ag_dblgauss.py
rayoptics/codev/tests/ag_dblgauss.seq
rayoptics/codev/tests/ag_dblgauss_s.csv
rayoptics/codev/tests/asp46.seq
rayoptics/codev/tests/dar_test.seq
rayoptics/codev/tests/dec_rev_tilt_test.seq
rayoptics/codev/tests/dec_test.seq
rayoptics/codev/tests/dec_tilt_test.seq
rayoptics/codev/tests/folded_lenses.seq
rayoptics/codev/tests/landscape_lens.seq
rayoptics/codev/tests/lens_reflection_test.seq
rayoptics/codev/tests/mangin.seq
rayoptics/codev/tests/paraboloid.seq
rayoptics/codev/tests/paraboloid_f8.seq
rayoptics/codev/tests/questar35.seq
rayoptics/codev/tests/rc_f16.seq
rayoptics/codev/tests/schmidt.seq
rayoptics/codev/tests/schmidt_sph.seq
rayoptics/codev/tests/singlet.seq
rayoptics/codev/tests/test.seq
rayoptics/codev/tests/test_reader.py
rayoptics/codev/tests/threemir.seq
rayoptics/codev/tests/threemrc.lis
rayoptics/codev/tests/threemrc_qbfs.lis
rayoptics/codev/tests/tilt_test.seq
rayoptics/codev/tests/unfolded_lenses_w_ape.seq
rayoptics/elem/__init__.py
rayoptics/elem/elements.py
rayoptics/elem/layout.py
rayoptics/elem/parttree.py
rayoptics/elem/profiles.py
rayoptics/elem/sgz2ele.py
rayoptics/elem/surface.py
rayoptics/elem/transform.py
rayoptics/elem/tests/ACL3026U-Zemax(ZMX).smx
rayoptics/elem/tests/ACL3026U-Zemax(ZMX).zmx
rayoptics/elem/tests/test_flip_ele.py
rayoptics/elem/tests/test_lens_entry_1.py
rayoptics/elem/tests/test_mirror_entry_1.py
rayoptics-0.9.8.dist-info/licenses/AUTHORS.rst
rayoptics-0.9.8.dist-info/licenses/LICENSE
rayoptics-0.9.8.dist-info/METADATA
rayoptics-0.9.8.dist-info/WHEEL
rayoptics-0.9.8.dist-info/entry_points.txt
rayoptics-0.9.8.dist-info/top_level.txt
rayoptics-0.9.8.dist-info/RECORD
