Metadata-Version: 2.4
Name: rayoptics
Version: 0.9.8
Summary: Tools for image forming optical design and analysis
Home-page: https://github.com/mjhoptics/ray-optics
Author: Michael J Hayford
Author-email: mjhoptics@gmail.com
License: BSD 3 Clause
Keywords: geometric optics, ray tracing, image forming optics,,paraxial optics, optical design, lens design,,aberrations, opd, psf
Platform: any
Classifier: Programming Language :: Python :: 3.11
Classifier: Programming Language :: Python :: 3.12
Classifier: Programming Language :: Python :: 3.13
Classifier: Operating System :: OS Independent
Classifier: Topic :: Scientific/Engineering :: Physics
Requires-Python: >=3.11
License-File: LICENSE
License-File: AUTHORS.rst
Requires-Dist: opticalglass>=1.1.1
Requires-Dist: numpy>=2.3.1
Requires-Dist: scipy>=1.16.0
Requires-Dist: matplotlib>=3.10.3
Requires-Dist: pandas>=2.2.3
Requires-Dist: anytree>=2.13.0
Requires-Dist: parsimonious>=0.10.0
Requires-Dist: transforms3d>=0.4.2
Requires-Dist: requests>=2.32.4
Requires-Dist: packaging>=25.0
Requires-Dist: json_tricks>=3.17.3
Requires-Dist: deprecation>=2.1.0
Requires-Dist: ipywidgets>=8.1.7
Requires-Dist: pyside6>=6.9.1
Requires-Dist: qdarkstyle>=3.2.3
Requires-Dist: qtconsole>=5.6.1
Requires-Dist: ipython>=9.2.0
Requires-Dist: traitlets>=5.14.3
Provides-Extra: testing
Requires-Dist: pytest; extra == "testing"
Requires-Dist: pytest-cov; extra == "testing"
Dynamic: license-file
